{"info": {"creator": "세명소프트", "description": "관광 특화 말뭉치"}, "tour_info": {"file_name": "관광 콘텐츠_문화 활동_레저스포츠_온라인_구글_건등낚시터_E_25_231029.csv", "Main_cate": "관광 콘텐츠", "2nd_cate": "문화 활동", "3rd_cate": "레저스포츠", "method": "온라인", "source": "구글", "Tourist Spot": "건등낚시터", "location": "E", "docu_num": "25", "date": "231029"}, "docu_info": {"content": "건등낚시터", "contains": "관광지명 건등낚시터 개요 건등낚시터는 동물원 및 관광농원으로 운영되며, 내방객들을 위해 다양한 체험과 볼거리를 제공합니다 휴게실, 식당, 매점, 샤워실, 화장실, 주차시설 등의 다양한 편의시설이 갖춰져 있습니다 이 곳에서는 송어, 잉어, 붕어, 향어, 메기 등 다양한 어종을 대상으로 대낚시, 루어, 프라이 낚시 등의 낚시 방법을 즐길 수 있습니다. 주소(AD) 강원특별자치도 원주시 문막읍 건등리 137-2 일정(DA) 연중무휴", "count": "50", "sentences": [{"sentcenceId": "0001", "sentence": "관광지명 건등낚시터", "annotations": [{"TagText": "건등낚시터", "TagId": "001", "Tagclass": "O", "TagCode": "LC", "startPos": 5, "endPos": 9}], "sentence_Tagclass": ""}, {"sentcenceId": "0002", "sentence": "개요 건등낚시터는 동물원 및 관광농원으로 운영되며, 내방객들을 위해 다양한 체험과 볼거리를 제공합니다", "annotations": [{"TagText": "다양한", "TagId": "001", "Tagclass": "E", "TagCode": "P", "startPos": 38, "endPos": 40}], "sentence_Tagclass": "P"}, {"sentcenceId": "0003", "sentence": "휴게실, 식당, 매점, 샤워실, 화장실, 주차시설 등의 다양한 편의시설이 갖춰져 있습니다", "annotations": null, "sentence_Tagclass": ""}, {"sentcenceId": "0004", "sentence": "이 곳에서는 송어, 잉어, 붕어, 향어, 메기 등 다양한 어종을 대상으로 대낚시, 루어, 프라이 낚시 등의 낚시 방법을 즐길 수 있습니다.", "annotations": [{"TagText": "낚시", "TagId": "001", "Tagclass": "O", "TagCode": "CV", "startPos": 54, "endPos": 55}], "sentence_Tagclass": ""}, {"sentcenceId": "0005", "sentence": "주소(AD) 강원특별자치도 원주시 문막읍 건등리 137-2", "annotations": [{"TagText": "강원특별자치도", "TagId": "001", "Tagclass": "A", "TagCode": "AD", "startPos": 7, "endPos": 13}, {"TagText": "원주시", "TagId": "002", "Tagclass": "A", "TagCode": "AD", "startPos": 15, "endPos": 17}, {"TagText": "문막읍", "TagId": "003", "Tagclass": "A", "TagCode": "AD", "startPos": 19, "endPos": 21}, {"TagText": "건등리", "TagId": "004", "Tagclass": "A", "TagCode": "AD", "startPos": 23, "endPos": 25}, {"TagText": "137-2", "TagId": "005", "Tagclass": "A", "TagCode": "AD", "startPos": 27, "endPos": 31}], "sentence_Tagclass": ""}, {"sentcenceId": "0006", "sentence": "일정(DA) 연중무휴", "annotations": [{"TagText": "연중무휴", "TagId": "001", "Tagclass": "A", "TagCode": "DA", "startPos": 7, "endPos": 10}], "sentence_Tagclass": ""}], "TagCount": {"T_TagCount": 9, "O_TagCount": 2, "A_TagCount": 6, "E_TagCount": 1}}}